{
  "_QPVersion": "0.1.1",
  "name": "${mod_name}",
  "id": "${mod_id}",
  "author": "Goobie, LookAtHippo, EnderdracheLP, cubic",
  "porter": "EnderdracheLP, cubic, RedBrumbler",
  "version": "${version}",
  "packageId": "com.beatgames.beatsaber",
  "packageVersion": "1.40.6_6407",
  "description": "Adds custom songs to Beat Saber Multiplayer.",
  "coverImage": "Cover.png",
  "dependencies": [],
  "modFiles": [],
  "lateModFiles": ["${binary}"],
  "libraryFiles": [],
  "fileCopies": [],
  "copyExtensions": []
}
